logutils/__init__.py
logutils/palettes.py
logutils_serpucga-0.2.2.dist-info/METADATA
logutils_serpucga-0.2.2.dist-info/WHEEL
logutils_serpucga-0.2.2.dist-info/top_level.txt
logutils_serpucga-0.2.2.dist-info/RECORD
