Metadata-Version: 2.4
Name: logutils_serpucga
Version: 0.2.2
Summary: Tools to generate pretty logs quickly using default logging library
Home-page: https://gitlab.com/Serbaf/logging_utils
Author: Sergio Puche García
Author-email: spuche@upv.es
License: GPL3
Dynamic: author
Dynamic: author-email
Dynamic: description
Dynamic: description-content-type
Dynamic: home-page
Dynamic: license
Dynamic: summary
